stationd/__init__.py
stationd/__main__.py
stationd/_version.py
stationd/accessory.py
stationd/amplifier.py
stationd/stationd.py
uniclogs_stationd-1.0.1.dist-info/licenses/LICENSE
uniclogs_stationd-1.0.1.dist-info/METADATA
uniclogs_stationd-1.0.1.dist-info/WHEEL
uniclogs_stationd-1.0.1.dist-info/top_level.txt
uniclogs_stationd-1.0.1.dist-info/RECORD
