Metadata-Version: 2.4
Name: uniclogs-stationd
Version: 1.0.1
Summary: A power management Daemon for UniClOGS.
Author: Steven Borrego, Bryan Borgeson
License: GPL-3.0
Requires-Python: >=3.11
License-File: LICENSE
Requires-Dist: gpiod>=2.3.0
Provides-Extra: dev
Requires-Dist: sphinx; extra == "dev"
Requires-Dist: mypy>=1.17.0; extra == "dev"
Requires-Dist: pytest>=9.0.0; extra == "dev"
Requires-Dist: pytest-cov>=7.0.0; extra == "dev"
Requires-Dist: ruff>=0.12.5; extra == "dev"
Requires-Dist: setuptools>=80; extra == "dev"
Requires-Dist: setuptools-scm>=9; extra == "dev"
Dynamic: license-file
